setup.py
sentry_tracpost/__init__.py
sentry_tracpost/plugin.py
sentry_tracpost/urls.py
sentry_tracpost.egg-info/PKG-INFO
sentry_tracpost.egg-info/SOURCES.txt
sentry_tracpost.egg-info/dependency_links.txt
sentry_tracpost.egg-info/entry_points.txt
sentry_tracpost.egg-info/not-zip-safe
sentry_tracpost.egg-info/requires.txt
sentry_tracpost.egg-info/top_level.txt