Metadata-Version: 1.1
Name: sentry-tracpost
Version: 0.2.9
Summary: A Sentry extension which integrates with Trac
Home-page: UNKNOWN
Author: Josh Harwood
Author-email: jharwood@joinerysoft.com
License: BSD
Platform: UNKNOWN
Classifier: Framework :: Django
Classifier: Intended Audience :: Developers
Classifier: Intended Audience :: System Administrators
Classifier: Operating System :: OS Independent
Classifier: Topic :: Software Development
